[
  {
    "id": 1,
    "month": "Mar",
    "investment": 30000,
    "sell": 241,
    "revenue": 10401
  },
  {
    "id": 2,
    "month": "Apr",
    "investment": 20000,
    "sell": 423,
    "revenue": 24500
  },
  {
    "id": 3,
    "month": "May",
    "investment": 80000,
    "sell": 726,
    "revenue": 67010
  },
  {
    "id": 4,
    "month": "Jun",
    "investment": 40000,
    "sell": 529,
    "revenue": 50405
  },
  {
    "id": 5,
    "month": "Jul",
    "investment": 70000,
    "sell": 601,
    "revenue": 50900
  },
  {
    "id": 6,
    "month": "Aug",
    "investment": 90000,
    "sell": 670,
    "revenue": 61000
  }
]
